Metadata-Version: 2.1
Name: satellite_image_classifier
Version: 0.3.0
Summary: A package for satellite image classification
Home-page: https://github.com/yourusername/satellite_image_classifier
Author: Your Name
Author-email: your.email@example.com
Classifier: Programming Language :: Python :: 3
Classifier: License :: OSI Approved :: MIT License
Classifier: Operating System :: OS Independent
Requires-Python: >=3.6
Requires-Dist: rasterio
Requires-Dist: numpy
Requires-Dist: scikit-learn
Requires-Dist: fiona
Requires-Dist: shapely
Requires-Dist: matplotlib
Requires-Dist: pandas
Requires-Dist: joblib
